filehash/__init__.py
filehash/filehash.py
filehash/filehash_cli.py
filehash-0.1.dev7.dist-info/AUTHORS.rst
filehash-0.1.dev7.dist-info/LICENSE
filehash-0.1.dev7.dist-info/METADATA
filehash-0.1.dev7.dist-info/WHEEL
filehash-0.1.dev7.dist-info/entry_points.txt
filehash-0.1.dev7.dist-info/top_level.txt
filehash-0.1.dev7.dist-info/RECORD
