Metadata-Version: 2.1
Name: filehash
Version: 0.1.dev7
Summary: Module and command-line tool that wraps around hashlib and zlib to facilitate generating checksums / hashes of files and directories.
Home-page: https://github.com/leonidessaguisagjr/filehash
Author: Leonides T. Saguisag Jr.
Author-email: leonidessaguisagjr@gmail.com
License: MIT
Platform: UNKNOWN
Classifier: Development Status :: 3 - Alpha
Classifier: Environment :: Console
Classifier: Intended Audience :: Developers
Classifier: Intended Audience :: End Users/Desktop
Classifier: License :: OSI Approved :: MIT License
Classifier: Programming Language :: Python
Classifier: Programming Language :: Python :: 2
Classifier: Programming Language :: Python :: 2.7
Classifier: Programming Language :: Python :: 3
Classifier: Programming Language :: Python :: 3.6
Classifier: Programming Language :: Python :: 3.7
Classifier: Programming Language :: Python :: 3.8
Classifier: Programming Language :: Python :: 3.9
Classifier: Programming Language :: Python :: 3.10
Classifier: Topic :: Software Development :: Libraries
Classifier: Topic :: Utilities
License-File: LICENSE
License-File: AUTHORS.rst
